eventgeometry/_eventgeometry.cpython-36m-i386-linux-gnu.so
eventgeometry/__init__.py
eventgeometry/eventgeometry.py
EventGeometry-1.0.1.dist-info/top_level.txt
EventGeometry-1.0.1.dist-info/WHEEL
EventGeometry-1.0.1.dist-info/METADATA
EventGeometry-1.0.1.dist-info/COPYING
EventGeometry-1.0.1.dist-info/RECORD
EventGeometry.libs/libgomp-2716b9e4.so.1.0.0
