Metadata-Version: 2.1
Name: EventGeometry
Version: 1.0.1
Summary: FastJet Contrib for computing the Energy Mover's Distance and related geometric quantities
Home-page: https://github.com/pkomiske/EventGeometry
Author: Patrick T. Komiske III
Author-email: pkomiske@mit.edu
License: GPLv2
Keywords: distance,earth mover's distance,energy mover's distance,emd,fastjet,fjcontrib,hidden geometry,metric,optimal transport,ot,particle physics,wasserstein
Platform: UNKNOWN
Classifier: Development Status :: 5 - Production/Stable
Classifier: Intended Audience :: Science/Research
Classifier: License :: OSI Approved :: GNU General Public License v3 (GPLv3)
Classifier: Natural Language :: English
Classifier: Operating System :: MacOS
Classifier: Operating System :: Microsoft :: Windows
Classifier: Operating System :: POSIX :: Linux
Classifier: Operating System :: Unix
Classifier: Programming Language :: C++
Classifier: Programming Language :: Python
Classifier: Programming Language :: Python :: Implementation :: CPython
Classifier: Programming Language :: Python :: 3
Classifier: Programming Language :: Python :: 3 :: Only
Classifier: Programming Language :: Python :: 3.6
Classifier: Programming Language :: Python :: 3.7
Classifier: Programming Language :: Python :: 3.8
Classifier: Programming Language :: Python :: 3.9
Classifier: Topic :: Scientific/Engineering
Classifier: Topic :: Scientific/Engineering :: Information Analysis
Classifier: Topic :: Scientific/Engineering :: Mathematics
Classifier: Topic :: Scientific/Engineering :: Physics
Classifier: Topic :: Software Development :: Libraries :: Python Modules
Requires-Python: >=3.6
License-File: COPYING
Requires-Dist: numpy (>=1.12.0)
Requires-Dist: pyfjcore (>=1.0.0)
Requires-Dist: wurlitzer (>=2.0.0)
